jlmc/__init__.py
jlmc/_version.py
jlmc/handlers.py
jlmc/labextension/package.json
jlmc/labextension/static/137.f99fdaeb63f6cd20664c.js
jlmc/labextension/static/163.3e183cc23ba813667994.js
jlmc/labextension/static/163.3e183cc23ba813667994.js.LICENSE.txt
jlmc/labextension/static/172.5c064f9af0b278ea71e8.js
jlmc/labextension/static/312.0d076610b072447500f3.js
jlmc/labextension/static/312.0d076610b072447500f3.js.LICENSE.txt
jlmc/labextension/static/34.36162f2d4f1d2bf777a5.js
jlmc/labextension/static/34.36162f2d4f1d2bf777a5.js.LICENSE.txt
jlmc/labextension/static/44.5ba88485e511d5dc50e6.js
jlmc/labextension/static/456.1c336aed2f88e16a6b2a.js
jlmc/labextension/static/456.1c336aed2f88e16a6b2a.js.LICENSE.txt
jlmc/labextension/static/479.3de39144c2ea9ecb3b59.js
jlmc/labextension/static/532.a2de02be4c84197d64ba.js
jlmc/labextension/static/549.504770e595e075b79eda.js
jlmc/labextension/static/57.f975a13e93882aa63dcf.js
jlmc/labextension/static/700.6922404e159f210e7ab6.js
jlmc/labextension/static/remoteEntry.030f5b48e2d85bcbe07a.js
jlmc/labextension/static/style.js
jlmc/labextension/static/third-party-licenses.json
jlmc/model_card_source/cell_deps.js
jlmc/model_card_source/cell_utils.js
jlmc/model_card_source/graph.js
jlmc/model_card_source/infocell.js
jlmc/model_card_source/main.js
jlmc/model_card_source/es5/cell.d.ts
jlmc/model_card_source/es5/cell.js
jlmc/model_card_source/es5/cell.js.map
jlmc/model_card_source/es5/cellslice.d.ts
jlmc/model_card_source/es5/cellslice.js
jlmc/model_card_source/es5/cellslice.js.map
jlmc/model_card_source/es5/control-flow.d.ts
jlmc/model_card_source/es5/control-flow.js
jlmc/model_card_source/es5/control-flow.js.map
jlmc/model_card_source/es5/data-flow.d.ts
jlmc/model_card_source/es5/data-flow.js
jlmc/model_card_source/es5/data-flow.js.map
jlmc/model_card_source/es5/graph.d.ts
jlmc/model_card_source/es5/graph.js
jlmc/model_card_source/es5/graph.js.map
jlmc/model_card_source/es5/index.d.ts
jlmc/model_card_source/es5/index.js
jlmodelcards-0.0.14.dist-info/LICENSE
jlmodelcards-0.0.14.dist-info/METADATA
jlmodelcards-0.0.14.dist-info/WHEEL
jlmodelcards-0.0.14.dist-info/top_level.txt
jlmodelcards-0.0.14.dist-info/RECORD
