Metadata-Version: 2.1
Name: jlmodelcards
Version: 0.0.14
Summary: Generating model cards for models in Jupyter Notebook.
Home-page: UNKNOWN
Author: kast
License: BSD-3-Clause
Keywords: Jupyter,JupyterLab,JupyterLab3
Platform: Linux
Platform: Mac OS X
Platform: Windows
Classifier: License :: OSI Approved :: BSD License
Classifier: Programming Language :: Python
Classifier: Programming Language :: Python :: 3
Classifier: Programming Language :: Python :: 3.6
Classifier: Programming Language :: Python :: 3.7
Classifier: Programming Language :: Python :: 3.8
Classifier: Programming Language :: Python :: 3.9
Classifier: Framework :: Jupyter
Requires-Python: >=3.6
License-File: LICENSE
Requires-Dist: jupyterlab (>=3.0)
